RTN/__init__.py
RTN/cli.py
RTN/exceptions.py
RTN/extras.py
RTN/fetch.py
RTN/file_parser.py
RTN/models.py
RTN/parser.py
RTN/patterns.py
RTN/ranker.py
rank_torrent_name-1.10.0.dist-info/LICENSE
rank_torrent_name-1.10.0.dist-info/METADATA
rank_torrent_name-1.10.0.dist-info/WHEEL
rank_torrent_name-1.10.0.dist-info/entry_points.txt
rank_torrent_name-1.10.0.dist-info/RECORD
