Metadata-Version: 2.3
Name: rank-torrent-name
Version: 1.10.0
Summary: Rank filenames based on user-defined rules!
License: MIT
Author: Spoked
Author-email: dreu.lavelle@gmail.com
Requires-Python: >=3.11,<4.0
Classifier: License :: OSI Approved :: MIT License
Classifier: Programming Language :: Python :: 3
Classifier: Programming Language :: Python :: 3.11
Classifier: Programming Language :: Python :: 3.12
Classifier: Programming Language :: Python :: 3.13
Requires-Dist: levenshtein (>=0.27.1,<0.28.0)
Requires-Dist: orjson (>=3.10.15,<4.0.0)
Requires-Dist: parsett (>=1.8.2,<2.0.0)
Requires-Dist: pydantic (>=2.6.3,<3.0.0)
Requires-Dist: pymediainfo (>=7.0.1,<8.0.0)
Project-URL: Repository, https://github.com/dreulavelle/rank-torrent-name
